sphinx_autosummary_accessors/__init__.py
sphinx_autosummary_accessors/autosummary.py
sphinx_autosummary_accessors/documenters.py
sphinx_autosummary_accessors/templates.py
sphinx_autosummary_accessors/templates/autosummary/accessor.rst
sphinx_autosummary_accessors/templates/autosummary/accessor_attribute.rst
sphinx_autosummary_accessors/templates/autosummary/accessor_callable.rst
sphinx_autosummary_accessors/templates/autosummary/accessor_method.rst
sphinx_autosummary_accessors-2025.3.1.dist-info/LICENSE
sphinx_autosummary_accessors-2025.3.1.dist-info/METADATA
sphinx_autosummary_accessors-2025.3.1.dist-info/WHEEL
sphinx_autosummary_accessors-2025.3.1.dist-info/top_level.txt
sphinx_autosummary_accessors-2025.3.1.dist-info/RECORD
