Metadata-Version: 2.2
Name: sphinx-autosummary-accessors
Version: 2025.3.1
Summary: sphinx autosummary extension to properly format pandas or xarray accessors
Author-email: Justus Magin <keewis@posteo.de>
License: MIT
Project-URL: Home, https://github.com/xarray-contrib/sphinx-autosummary-accessors
Project-URL: Documentation, https://sphinx-autosummary-accessors.readthedocs.io/en/stable
Classifier: License :: OSI Approved :: MIT License
Classifier: Operating System :: OS Independent
Classifier: Programming Language :: Python :: 3
Classifier: Programming Language :: Python :: 3.9
Classifier: Programming Language :: Python :: 3.10
Classifier: Programming Language :: Python :: 3.11
Classifier: Programming Language :: Python :: 3.12
Classifier: Programming Language :: Python :: 3.13
Requires-Python: >=3.9
License-File: LICENSE
Requires-Dist: sphinx>=5.3
Requires-Dist: packaging
